materialx/__init__.py
materialx/__meta__.py
materialx/emoji.py
mkdocs_material_extensions-1.0.2.dist-info/LICENSE.md
mkdocs_material_extensions-1.0.2.dist-info/METADATA
mkdocs_material_extensions-1.0.2.dist-info/WHEEL
mkdocs_material_extensions-1.0.2.dist-info/top_level.txt
mkdocs_material_extensions-1.0.2.dist-info/RECORD
